<annotation>
	<folder>images</folder>
	<filename>178.jpg</filename>
	<path>F:\Desktop\Thesis\Dataset\final\images\178.jpg</path>
	<source>
		<database>Unknown</database>
	</source>
	<size>
		<width>800</width>
		<height>600</height>
		<depth>3</depth>
	</size>
	<segmented>0</segmented>
	<object>
		<name>smoke</name>
		<pose>Unspecified</pose>
		<truncated>0</truncated>
		<difficult>0</difficult>
		<bndbox>
			<xmin>347</xmin>
			<ymin>271</ymin>
			<xmax>764</xmax>
			<ymax>541</ymax>
		</bndbox>
	</object>
</annotation>
